syntaxi/__init__.py
syntaxi/shift.py
syntaxi/syntaxi.py
syntaxi/tokens.py
syntaxi-0.1.7.dist-info/LICENSE
syntaxi-0.1.7.dist-info/METADATA
syntaxi-0.1.7.dist-info/WHEEL
syntaxi-0.1.7.dist-info/RECORD
