Metadata-Version: 2.1
Name: syntaxi
Version: 0.1.7
Summary: Make your tokenizer more syntax-friendly.
Home-page: https://github.com/nilq/syntaxi
License: MIT
Author: Niels Horn
Author-email: niels@horn.ninja
Requires-Python: >=3.11,<4.0
Classifier: License :: OSI Approved :: MIT License
Classifier: Programming Language :: Python :: 3
Classifier: Programming Language :: Python :: 3.11
Classifier: Programming Language :: Python :: 3.12
Requires-Dist: regex (>=2023.12.25,<2024.0.0)
Requires-Dist: tokenizers (>=0.15.2,<0.16.0)
Project-URL: Repository, https://github.com/nilq/syntaxi
